<?xml version="1.0" encoding="UTF-8" ?>
<!DOCTYPE ldml SYSTEM "../../common/dtd/ldml.dtd">
<!-- Copyright © 1991-2024 Unicode, Inc.
For terms of use, see http://www.unicode.org/copyright.html
SPDX-License-Identifier: Unicode-3.0
CLDR data files are interpreted according to the LDML specification (http://unicode.org/reports/tr35/)
-->
<ldml>
	<identity>
		<version number="$Revision$"/>
		<language type="ha"/>
		<territory type="NE"/>
	</identity>
	<localeDisplayNames>
		<languages>
			<language type="en_CA">Turanci Kanada</language>
			<language type="en_GB">Turanci Biritaniya</language>
			<language type="en_GB" alt="short">Turancin Ingila</language>
			<language type="en_US">Turanci Amirka</language>
			<language type="en_US" alt="short">Turancin Amurka</language>
			<language type="fa">Farisa</language>
			<language type="ff">Fulah</language>
			<language type="hi_Latn">Hindi (Latinanci)</language>
			<language type="hi_Latn" alt="variant">Hinglish</language>
			<language type="jv">Jafananci</language>
			<language type="ko">Harshen Koreya</language>
			<language type="ms">Harshen Malai</language>
			<language type="sah">Sakha</language>
			<language type="xh">Bazosa</language>
		</languages>
		<scripts>
			<script type="Armn">Armeniyawa</script>
			<script type="Cans">Haɗaɗɗun Gaɓoɓin Ƴan Asali na Kanada</script>
			<script type="Grek">Girka</script>
			<script type="Hans">Sauƙaƙaƙƙen</script>
			<script type="Jamo">Jamo</script>
			<script type="Thai">Thai</script>
		</scripts>
		<territories>
			<territory type="053">Asturesiya</territory>
			<territory type="AR">Arjantiniya</territory>
			<territory type="BD">Bangiladas</territory>
			<territory type="BH">Baharan</territory>
			<territory type="CK">Tsibiran Kuku</territory>
			<territory type="CL">Cayile</territory>
			<territory type="CV">Tsibiran Kap Barde</territory>
			<territory type="CY">Sifurus</territory>
			<territory type="CZ">Jamhuriyar Cak</territory>
			<territory type="GE">Jiwarjiya</territory>
			<territory type="GQ">Gini Ta Ikwaita</territory>
			<territory type="GU">Gwam</territory>
			<territory type="IM">Isle na Mutum</territory>
			<territory type="KW">Kwiyat</territory>
			<territory type="LA">Lawas</territory>
			<territory type="ME">Mantanegara</territory>
			<territory type="MY">Malaisiya</territory>
			<territory type="NU">Niyu</territory>
			<territory type="PN">Pitakarin</territory>
			<territory type="TL">Timor Ta Gabas</territory>
			<territory type="VA">Batikan</territory>
			<territory type="XA">Gogewar Kwalwa</territory>
			<territory type="XB">Gano wani abu ta hanyar amfani da fasaha</territory>
			<territory type="YE">Yamal</territory>
		</territories>
		<keys>
			<key type="hc">Zagayen Awowi</key>
		</keys>
		<types>
			<type key="hc" type="h11">Tsarin Awowi 12(0–11)</type>
		</types>
		<measurementSystemNames>
			<measurementSystemName type="UK">Tsarin awo kasar Ingila</measurementSystemName>
			<measurementSystemName type="US">Amurka</measurementSystemName>
		</measurementSystemNames>
	</localeDisplayNames>
	<characters>
		<exemplarCharacters type="auxiliary">[áàâ éèê íìî óòô p q {r̃} úùû v x {ʼy}]</exemplarCharacters>
		<exemplarCharacters type="index">[A B Ɓ C D Ɗ E F G H I J K Ƙ L M N O P Q R S T U V W X Y Ƴ Z]</exemplarCharacters>
	</characters>
	<dates>
		<fields>
			<field type="year">
				<relativeTime type="past">
					<relativeTimePattern count="one">shekara {0} da ta gabata</relativeTimePattern>
					<relativeTimePattern count="other">shekara da suka gabata {0}</relativeTimePattern>
				</relativeTime>
			</field>
			<field type="quarter">
				<relativeTime type="past">
					<relativeTimePattern count="one">kwata da suka gabata {0}</relativeTimePattern>
					<relativeTimePattern count="other">kwatas da suka gabata {0}</relativeTimePattern>
				</relativeTime>
			</field>
			<field type="month">
				<relativeTime type="past">
					<relativeTimePattern count="one">watan da ya gabata</relativeTimePattern>
					<relativeTimePattern count="other">watanni da suka gabata {0}}</relativeTimePattern>
				</relativeTime>
			</field>
			<field type="month-short">
				<relativeTime type="past">
					<relativeTimePattern count="one">wata {0} da ya gabata</relativeTimePattern>
					<relativeTimePattern count="other">watan da ya gabata {0}</relativeTimePattern>
				</relativeTime>
			</field>
			<field type="month-narrow">
				<relativeTime type="past">
					<relativeTimePattern count="one">watan da ya gabata {0}</relativeTimePattern>
					<relativeTimePattern count="other">watanni {0} da suka gabata</relativeTimePattern>
				</relativeTime>
			</field>
			<field type="week">
				<relativeTime type="past">
					<relativeTimePattern count="one">mako da ya gabata {0}</relativeTimePattern>
					<relativeTimePattern count="other">makonni da suka gabata {0}</relativeTimePattern>
				</relativeTime>
			</field>
			<field type="week-short">
				<relativeTime type="future">
					<relativeTimePattern count="one">a cikin mako {0}</relativeTimePattern>
					<relativeTimePattern count="other">a cikin mako {0}</relativeTimePattern>
				</relativeTime>
				<relativeTime type="past">
					<relativeTimePattern count="one">mako {0} da ya gabata</relativeTimePattern>
					<relativeTimePattern count="other">mako da ya gabata {0}</relativeTimePattern>
				</relativeTime>
			</field>
			<field type="week-narrow">
				<relativeTime type="past">
					<relativeTimePattern count="one">mako da suka gabata {0}</relativeTimePattern>
					<relativeTimePattern count="other">mako {0} da ya gabata</relativeTimePattern>
				</relativeTime>
			</field>
			<field type="day">
				<relativeTime type="future">
					<relativeTimePattern count="one">a cikin rana {0}</relativeTimePattern>
					<relativeTimePattern count="other">a cikin kwanaki {0}</relativeTimePattern>
				</relativeTime>
				<relativeTime type="past">
					<relativeTimePattern count="one">rana da ya gabata {0}</relativeTimePattern>
					<relativeTimePattern count="other">kwanaki da suka gabata {0}</relativeTimePattern>
				</relativeTime>
			</field>
			<field type="sun">
				<relativeTime type="future">
					<relativeTimePattern count="one">cikin Lahadi {0}</relativeTimePattern>
					<relativeTimePattern count="other">cikin {0} Lahadi</relativeTimePattern>
				</relativeTime>
				<relativeTime type="past">
					<relativeTimePattern count="one">Lahadi {0} da ta gabata</relativeTimePattern>
					<relativeTimePattern count="other">{0} Lahadin da ta gabata</relativeTimePattern>
				</relativeTime>
			</field>
			<field type="mon">
				<relative type="-1">Litinin din da ta gabata</relative>
				<relative type="0">wannan Litinin din</relative>
				<relative type="1">Litinin din da ya gabata</relative>
				<relativeTime type="future">
					<relativeTimePattern count="one">cikin Litinin {0}</relativeTimePattern>
					<relativeTimePattern count="other">cikin {0} Litinin</relativeTimePattern>
				</relativeTime>
				<relativeTime type="past">
					<relativeTimePattern count="one">Litinin {0} da ta gabata</relativeTimePattern>
					<relativeTimePattern count="other">{0} Litinin din da ta gabata</relativeTimePattern>
				</relativeTime>
			</field>
			<field type="mon-narrow">
				<relativeTime type="past">
					<relativeTimePattern count="one">{0} Litinin din da ta</relativeTimePattern>
					<relativeTimePattern count="other">{0} Litinin din da ta</relativeTimePattern>
				</relativeTime>
			</field>
			<field type="tue">
				<relativeTime type="future">
					<relativeTimePattern count="one">cikin Talata {0}</relativeTimePattern>
					<relativeTimePattern count="other">cikin {0} Talata</relativeTimePattern>
				</relativeTime>
				<relativeTime type="past">
					<relativeTimePattern count="one">Talata {0} da ta gabata</relativeTimePattern>
					<relativeTimePattern count="other">{0} Talatar da ta gabata</relativeTimePattern>
				</relativeTime>
			</field>
			<field type="wed">
				<relativeTime type="future">
					<relativeTimePattern count="one">cikin Laraba {0}</relativeTimePattern>
					<relativeTimePattern count="other">cikin {0} Laraba</relativeTimePattern>
				</relativeTime>
				<relativeTime type="past">
					<relativeTimePattern count="one">Laraba {0} da ta gabata</relativeTimePattern>
					<relativeTimePattern count="other">{0} Laraba da ta gabata</relativeTimePattern>
				</relativeTime>
			</field>
			<field type="thu">
				<relativeTime type="future">
					<relativeTimePattern count="one">cikin Alhamis {0}</relativeTimePattern>
					<relativeTimePattern count="other">cikin {0} Alhamis</relativeTimePattern>
				</relativeTime>
				<relativeTime type="past">
					<relativeTimePattern count="one">Alhamis {0} da ta gabata</relativeTimePattern>
					<relativeTimePattern count="other">{0} Alhamis din da ya gabata</relativeTimePattern>
				</relativeTime>
			</field>
			<field type="fri">
				<relativeTime type="future">
					<relativeTimePattern count="one">cikin Jumaʼa {0}</relativeTimePattern>
					<relativeTimePattern count="other">cikin {0} Jumaʼa</relativeTimePattern>
				</relativeTime>
				<relativeTime type="past">
					<relativeTimePattern count="one">Jumaʼa {0} da ta wuce</relativeTimePattern>
					<relativeTimePattern count="other">{0} Jumaʼa da ta wuce</relativeTimePattern>
				</relativeTime>
			</field>
			<field type="sat">
				<relativeTime type="future">
					<relativeTimePattern count="one">cikin Asabar {0}</relativeTimePattern>
					<relativeTimePattern count="other">cikin {0} Asabar</relativeTimePattern>
				</relativeTime>
				<relativeTime type="past">
					<relativeTimePattern count="one">Asabar {0} da ta wuce</relativeTimePattern>
					<relativeTimePattern count="other">{0} Asabar din da ya wuce</relativeTimePattern>
				</relativeTime>
			</field>
			<field type="hour">
				<relativeTime type="future">
					<relativeTimePattern count="one">cikin awa {0}</relativeTimePattern>
					<relativeTimePattern count="other">cikin {0} awa</relativeTimePattern>
				</relativeTime>
				<relativeTime type="past">
					<relativeTimePattern count="one">awa {0} da ta gabata</relativeTimePattern>
					<relativeTimePattern count="other">{0} awa da ya gabata</relativeTimePattern>
				</relativeTime>
			</field>
			<field type="minute">
				<relativeTime type="future">
					<relativeTimePattern count="one">cikin minti {0}</relativeTimePattern>
					<relativeTimePattern count="other">cikin {0} minti</relativeTimePattern>
				</relativeTime>
				<relativeTime type="past">
					<relativeTimePattern count="one">minti {0} da ya gabata</relativeTimePattern>
					<relativeTimePattern count="other">{0} minti da ya gabata</relativeTimePattern>
				</relativeTime>
			</field>
			<field type="second">
				<relativeTime type="future">
					<relativeTimePattern count="one">cikin dakika {0}</relativeTimePattern>
					<relativeTimePattern count="other">cikin {0} dakika</relativeTimePattern>
				</relativeTime>
				<relativeTime type="past">
					<relativeTimePattern count="one">dakika {0} da ta gabata</relativeTimePattern>
					<relativeTimePattern count="other">{0} dakika da ya gabata</relativeTimePattern>
				</relativeTime>
			</field>
		</fields>
		<timeZoneNames>
			<metazone type="Africa_Southern">
				<long>
					<standard>South Africa Standard Time</standard>
				</long>
			</metazone>
			<metazone type="Arabian">
				<long>
					<generic>Lokacin Arebiya</generic>
					<standard>Arabian Standard Time</standard>
					<daylight>Lokacin Rana na Arebiya</daylight>
				</long>
			</metazone>
			<metazone type="Australia_Central">
				<long>
					<generic>Central Australia Time</generic>
					<standard>Tsayayyen Lokacin Tsakiyar Austiraliya</standard>
					<daylight>Lokacin Rana na Tsakiyar Austiraliya</daylight>
				</long>
			</metazone>
			<metazone type="Australia_Eastern">
				<long>
					<generic>Lokacin Gabashin Austiraliya</generic>
					<standard>Australian Eastern Standard Time</standard>
					<daylight>Lokacin Rana na Gabashin Austiraliya</daylight>
				</long>
			</metazone>
			<metazone type="Bhutan">
				<long>
					<standard>Bhutan Time</standard>
				</long>
			</metazone>
			<metazone type="Cape_Verde">
				<long>
					<generic>Lokacin Cape Verde</generic>
					<standard>Cape Verde Standard Time</standard>
					<daylight>Lokacin Bazara na Cape Verde</daylight>
				</long>
			</metazone>
			<metazone type="Georgia">
				<long>
					<generic>Lokacin Georgia</generic>
					<standard>Tsayayyen Lokacin Georgia</standard>
					<daylight>Georgia Summer Time</daylight>
				</long>
			</metazone>
			<metazone type="GMT">
				<long>
					<standard>Lokacin Greenwhich a London</standard>
				</long>
			</metazone>
			<metazone type="Gulf">
				<long>
					<standard>Lokacin Golf</standard>
				</long>
			</metazone>
			<metazone type="India">
				<long>
					<standard>India Standard Time</standard>
				</long>
			</metazone>
			<metazone type="Indonesia_Eastern">
				<long>
					<standard>Eastern Indonesia Time</standard>
				</long>
			</metazone>
			<metazone type="Israel">
				<long>
					<generic>Lokacin Israʼila</generic>
					<standard>Israel Standard Time</standard>
					<daylight>Israel Daylight Time</daylight>
				</long>
			</metazone>
			<metazone type="Japan">
				<long>
					<generic>Lokacin Japan</generic>
					<standard>Japan Standard Time</standard>
					<daylight>Japan Daylight Time</daylight>
				</long>
			</metazone>
			<metazone type="Tokelau">
				<long>
					<standard>Tokelau Time</standard>
				</long>
			</metazone>
			<metazone type="Turkmenistan">
				<long>
					<generic>Lokacin Turkmenistan</generic>
					<standard>Tsayayyen Lokacin Turkmenistan</standard>
					<daylight>Turkmenistan Summer Time</daylight>
				</long>
			</metazone>
		</timeZoneNames>
	</dates>
	<numbers>
		<decimalFormats numberSystem="latn">
			<decimalFormatLength type="short">
				<decimalFormat>
					<pattern type="1000" count="one">0D</pattern>
					<pattern type="1000" count="other">0D</pattern>
					<pattern type="10000" count="one">00D</pattern>
					<pattern type="10000" count="other">00D</pattern>
					<pattern type="100000" count="one">000D</pattern>
					<pattern type="100000" count="other">000D</pattern>
				</decimalFormat>
			</decimalFormatLength>
		</decimalFormats>
		<currencyFormats numberSystem="latn">
			<currencyFormatLength type="short">
				<currencyFormat type="standard">
					<pattern type="100000" count="one">¤ 000K</pattern>
					<pattern type="100000" count="other">¤ 000D</pattern>
				</currencyFormat>
			</currencyFormatLength>
			<unitPattern count="one">{0} {1}</unitPattern>
			<unitPattern count="other">{0} {1}</unitPattern>
		</currencyFormats>
		<currencies>
			<currency type="BOB">
				<displayName count="one">boliviano na ƙasar Bolivia</displayName>
				<displayName count="other">Boloviano na ƙasar Bolivia</displayName>
			</currency>
			<currency type="CLP">
				<displayName count="one">peso na ƙasar Chile</displayName>
				<displayName count="other">Peso na ƙasar Chile</displayName>
			</currency>
			<currency type="COP">
				<displayName count="one">peso na ƙasar Columbia</displayName>
				<displayName count="other">Peso na ƙasar Columbia</displayName>
			</currency>
			<currency type="CRC">
				<displayName count="one">colón na ƙasar Costa Rica</displayName>
				<displayName count="other">colón na ƙasar Costa Rica</displayName>
			</currency>
			<currency type="GYD">
				<displayName count="one">dalar Guyana</displayName>
				<displayName count="other">Dalar Guyana</displayName>
			</currency>
			<currency type="NIO">
				<displayName count="one">córdoba na ƙasar Nicaragua</displayName>
				<displayName count="other">Córdoba na ƙasar Nicaragua</displayName>
			</currency>
			<currency type="PAB">
				<displayName count="one">balboa na ƙasar Panama</displayName>
				<displayName count="other">Balboa na ƙasar Panama</displayName>
			</currency>
			<currency type="PEN">
				<displayName count="one">sol na ƙasar Peru</displayName>
				<displayName count="other">Sol na ƙasar Peru</displayName>
			</currency>
			<currency type="PHP">
				<displayName count="one">kuɗin Philippine</displayName>
				<displayName count="other">Kuɗin Philippine</displayName>
			</currency>
			<currency type="PYG">
				<displayName count="one">guarani na ƙasar Paraguay</displayName>
				<displayName count="other">Guarani na ƙasar Paraguay</displayName>
			</currency>
			<currency type="SRD">
				<displayName count="one">dalar ƙasar Suriname</displayName>
				<displayName count="other">Dalar ƙasar Suriname</displayName>
			</currency>
			<currency type="USD">
				<displayName count="one">Dalar Amirka</displayName>
				<displayName count="other">Dalar Amurka</displayName>
			</currency>
			<currency type="VES">
				<displayName count="one">bolívar na ƙasar Venezuela</displayName>
				<displayName count="other">Bolívar na ƙasar Venezuela</displayName>
			</currency>
		</currencies>
	</numbers>
	<units>
		<unitLength type="long">
			<compoundUnit type="10p2">
				<unitPrefixPattern>hekta{0}</unitPrefixPattern>
			</compoundUnit>
			<unit type="angle-revolution">
				<displayName>revolution</displayName>
			</unit>
			<unit type="graphics-em">
				<displayName>typographic em</displayName>
			</unit>
			<unit type="length-mile-scandinavian">
				<displayName>mile-scandinavian</displayName>
			</unit>
			<unit type="temperature-generic">
				<unitPattern count="one">Digirin yanayi {0}</unitPattern>
				<unitPattern count="other">digiri-digiri {0}</unitPattern>
			</unit>
			<unit type="torque-pound-force-foot">
				<displayName>pound-feet</displayName>
			</unit>
			<unit type="volume-dessert-spoon">
				<displayName>dessert spoon</displayName>
				<unitPattern count="one">dessert spoon {0}</unitPattern>
				<unitPattern count="other">dessert spoon {0}</unitPattern>
			</unit>
			<unit type="volume-dessert-spoon-imperial">
				<displayName>Imp. dessert spoon</displayName>
				<unitPattern count="one">Imp. dessert spoon {0}</unitPattern>
				<unitPattern count="other">Imp. dessert spoon {0}</unitPattern>
			</unit>
			<unit type="volume-dram">
				<displayName>dram</displayName>
				<unitPattern count="one">dram {0}</unitPattern>
				<unitPattern count="other">{0} dram</unitPattern>
			</unit>
			<unit type="volume-quart-imperial">
				<displayName>Imp. quart</displayName>
				<unitPattern count="one">Imp. quart {0}</unitPattern>
				<unitPattern count="other">Imp. quart {0}</unitPattern>
			</unit>
		</unitLength>
	</units>
</ldml>
